katsdpimager.libs/libgomp-f7e03b3e.so.1.0.0
katsdpimager-1.5.data/scripts/imager-mkat-report.py
katsdpimager-1.5.data/scripts/imager.py
katsdpimager-1.5.data/scripts/imager-mkat-pipeline.py
katsdpimager-1.5.dist-info/WHEEL
katsdpimager-1.5.dist-info/LICENSE
katsdpimager-1.5.dist-info/METADATA
katsdpimager-1.5.dist-info/top_level.txt
katsdpimager-1.5.dist-info/RECORD
katsdpimager/fft.py
katsdpimager/primary_beam.py
katsdpimager/sky_model.py
katsdpimager/profiling.py
katsdpimager/polarization.py
katsdpimager/loader_katdal.py
katsdpimager/beam.py
katsdpimager/loader_core.py
katsdpimager/loader.py
katsdpimager/parameters.py
katsdpimager/clean.py
katsdpimager/imaging.py
katsdpimager/metadata.py
katsdpimager/nvtx_build.py
katsdpimager/report.py
katsdpimager/progress.py
katsdpimager/_preprocess.cpython-36m-x86_64-linux-gnu.so
katsdpimager/nvtx.py
katsdpimager/image.py
katsdpimager/weight.py
katsdpimager/arguments.py
katsdpimager/fast_math.py
katsdpimager/_nvtx_real.py
katsdpimager/loader_ms.py
katsdpimager/frontend.py
katsdpimager/__init__.py
katsdpimager/predict.py
katsdpimager/types.py
katsdpimager/preprocess.py
katsdpimager/io.py
katsdpimager/_nvtx_fallback.py
katsdpimager/grid.py
katsdpimager/models/beams/meerkat/v1/beam_L.h5
katsdpimager/models/beams/meerkat/v1/beam_UHF.h5
katsdpimager/imager_kernels/apply_primary_beam.mako
katsdpimager/imager_kernels/layer_image.mako
katsdpimager/imager_kernels/fftshift.mako
katsdpimager/imager_kernels/scale.mako
katsdpimager/imager_kernels/degrid.mako
katsdpimager/imager_kernels/density_weights.mako
katsdpimager/imager_kernels/atomic.mako
katsdpimager/imager_kernels/mean_weight.mako
katsdpimager/imager_kernels/add_image.mako
katsdpimager/imager_kernels/grid_weights.mako
katsdpimager/imager_kernels/predict.mako
katsdpimager/imager_kernels/grid.mako
katsdpimager/imager_kernels/image_to_layer.mako
katsdpimager/imager_kernels/layer_to_image.mako
katsdpimager/imager_kernels/fourier_beam.mako
katsdpimager/imager_kernels/complex_to_real.mako
katsdpimager/imager_kernels/clean/find_peak.mako
katsdpimager/imager_kernels/clean/rank.mako
