Metadata-Version: 2.1
Name: katsdpimager
Version: 1.5
Summary: GPU-accelerated radio-astronomy spectral line imager
Home-page: https://github.com/ska-sa/katsdpimager/
Author: MeerKAT SDP Team
Author-email: sdpdev+katsdpimager@ska.ac.za
License: UNKNOWN
Platform: UNKNOWN
Classifier: Development Status :: 5 - Production/Stable
Classifier: License :: OSI Approved :: BSD License
Classifier: Programming Language :: Python :: 3 :: Only
Classifier: Topic :: Scientific/Engineering :: Astronomy
Classifier: Environment :: Console
Requires-Python: >=3.6
Requires-Dist: ansicolors
Requires-Dist: astropy (>=1.3)
Requires-Dist: h5py
Requires-Dist: katsdpsigproc[cuda] (>=1.2)
Requires-Dist: katpoint (<1)
Requires-Dist: numba
Requires-Dist: numpy (>=1.17.0)
Requires-Dist: progress (>=1.5)
Requires-Dist: scikit-cuda
Requires-Dist: scipy
Requires-Dist: contextvars ; python_version < "3.7"
Provides-Extra: benchmark
Requires-Dist: katpoint ; extra == 'benchmark'
Provides-Extra: cpu
Provides-Extra: doc
Requires-Dist: sphinx (>=1.3.0) ; extra == 'doc'
Requires-Dist: sphinxcontrib-tikz ; extra == 'doc'
Requires-Dist: sphinx-rtd-theme ; extra == 'doc'
Requires-Dist: nose ; extra == 'doc'
Requires-Dist: scipy ; extra == 'doc'
Requires-Dist: fakeredis[lua] ; extra == 'doc'
Provides-Extra: katdal
Requires-Dist: katdal (>=0.18) ; extra == 'katdal'
Requires-Dist: katsdpmodels[requests] ; extra == 'katdal'
Provides-Extra: ms
Requires-Dist: python-casacore ; extra == 'ms'
Provides-Extra: pipeline
Requires-Dist: bokeh (>=2.0.0) ; extra == 'pipeline'
Requires-Dist: jinja2 (>=2.11) ; extra == 'pipeline'
Requires-Dist: katdal[s3credentials] ; extra == 'pipeline'
Requires-Dist: katsdpservices ; extra == 'pipeline'
Requires-Dist: katsdpimageutils ; extra == 'pipeline'
Requires-Dist: matplotlib (>=3.1) ; extra == 'pipeline'
Provides-Extra: report
Requires-Dist: aplpy ; extra == 'report'
Requires-Dist: matplotlib ; extra == 'report'
Requires-Dist: mako ; extra == 'report'
Provides-Extra: test
Requires-Dist: nose ; extra == 'test'
Requires-Dist: scipy ; extra == 'test'
Requires-Dist: fakeredis[lua] ; extra == 'test'
